polynomialmathsolution_pms.py
polynomialmathsolution_pms-1.1.dist-info/METADATA
polynomialmathsolution_pms-1.1.dist-info/WHEEL
polynomialmathsolution_pms-1.1.dist-info/top_level.txt
polynomialmathsolution_pms-1.1.dist-info/RECORD
